<?xml version = '1.0' encoding = 'UTF-8'?>
<TableProxyOraclev11g class="oracle.dbtools.crest.model.design.storage.oracle.v11g.TableProxyOraclev11g" name="ASB_NOTIFICATION_LOG" directorySegmentName="seg_6" id="15070456-D18A-0066-57A3-458F8FA52C8E">
<createdBy>mgabua</createdBy>
<createdTime>2016-02-01 17:31:25 UTC</createdTime>
<ownerDesignName>maintenix</ownerDesignName>
<partitionedRowMovement>DISABLE</partitionedRowMovement>
<temporaryChanged>false</temporaryChanged>
<accessDriverType>oracle_loader</accessDriverType>
<rejectLimit></rejectLimit>
<columnProxies itemClass="oracle.dbtools.crest.model.design.storage.oracle.v12c.ColumnProxyOraclev12c">
<ColumnProxy name="BODY_BLOB" id="2C0A2591-E99F-5D29-FC45-9DE5A879BDE2">
<createdBy>mgabua</createdBy>
<createdTime>2016-02-01 17:31:27 UTC</createdTime>
<ownerDesignName>maintenix</ownerDesignName>
</ColumnProxy>
<ColumnProxy name="NOTIFICATION_SOURCE" id="314890F7-30E0-AB9E-F8C9-CBF72BE89AA9">
<createdBy>mgabua</createdBy>
<createdTime>2016-02-01 17:31:27 UTC</createdTime>
<ownerDesignName>maintenix</ownerDesignName>
<nncDeferrable>YES</nncDeferrable>
</ColumnProxy>
<ColumnProxy name="NOTIFICATION_ID" id="66E44587-0718-59FB-569E-693603148166">
<createdBy>mgabua</createdBy>
<createdTime>2016-02-01 17:31:27 UTC</createdTime>
<ownerDesignName>maintenix</ownerDesignName>
<nncDeferrable>YES</nncDeferrable>
</ColumnProxy>
<ColumnProxy name="RSTAT_CD" id="6EA75469-8AE2-D1D2-EF40-1D95014EB893">
<createdBy>mgabua</createdBy>
<createdTime>2016-02-01 17:31:27 UTC</createdTime>
<ownerDesignName>maintenix</ownerDesignName>
<defaultValue>0</defaultValue>
<deferrable>YES</deferrable>
<nncDeferrable>YES</nncDeferrable>
</ColumnProxy>
<ColumnProxy name="BINARY_BLOB" id="78BCEEAD-EA5D-B11E-9206-2C2D3C7CFC17">
<createdBy>mgabua</createdBy>
<createdTime>2016-02-01 17:31:27 UTC</createdTime>
<ownerDesignName>maintenix</ownerDesignName>
</ColumnProxy>
<ColumnProxy name="TRANSACTION_ID" id="90CD632E-97E1-F920-A7CA-4122C1409839">
<createdBy>mgabua</createdBy>
<createdTime>2016-02-01 17:31:27 UTC</createdTime>
<ownerDesignName>maintenix</ownerDesignName>
<nncDeferrable>YES</nncDeferrable>
</ColumnProxy>
<ColumnProxy name="NOTIFICATION_DATE" id="F8C95C5B-7C3E-6181-65E0-98E4681A5F89">
<createdBy>mgabua</createdBy>
<createdTime>2016-02-01 17:31:27 UTC</createdTime>
<ownerDesignName>maintenix</ownerDesignName>
<nncDeferrable>YES</nncDeferrable>
</ColumnProxy>
</columnProxies>
<indexProxies>
<IndexProxy class="oracle.dbtools.crest.model.design.storage.oracle.v10g.IndexProxyOraclev10g" name="IX_FK_MIMRSTAT_ASBNOTIFICATION" id="F69147A1-B576-9D31-E49F-64CCE41C0D86">
<createdBy>mgabua</createdBy>
<createdTime>2016-02-01 17:31:27 UTC</createdTime>
<ownerDesignName>maintenix</ownerDesignName>
<logging></logging>
</IndexProxy>
</indexProxies>
<foreignKeys>
<ForeignKey class="oracle.dbtools.crest.model.design.storage.oracle.v10g.FKProxyOraclev10g" name="FK_MIMRSTAT_ASBNOTIFICATION" id="20C3575F-28F1-E0D7-D7BA-BB745CA8D0DF">
<createdBy>mgabua</createdBy>
<createdTime>2016-02-01 17:31:33 UTC</createdTime>
<ownerDesignName>maintenix</ownerDesignName>
<deferrable>YES</deferrable>
</ForeignKey>
</foreignKeys>
<primaryKeys>
<PrimaryKey class="oracle.dbtools.crest.model.design.storage.oracle.v10g.PKProxyOraclev10g" name="PK_ASB_NOTIFICATION_LOG" id="A17BCCD5-94C7-B6CB-896E-9E4205E8B50F">
<createdBy>mgabua</createdBy>
<createdTime>2016-02-01 17:31:27 UTC</createdTime>
<ownerDesignName>maintenix</ownerDesignName>
<indexSort>SORTED</indexSort>
</PrimaryKey>
</primaryKeys>
</TableProxyOraclev11g>