<?xml version = '1.0' encoding = 'UTF-8'?>
<FKIndexAssociation class="oracle.dbtools.crest.model.design.relational.FKIndexAssociation" directorySegmentName="seg_26" id="C30162DF-EF3F-A69E-C843-28787F98B599" name="FK_REFFINDING_EQP_FINDING">
<sourceDDLFile>maintenix.sql</sourceDDLFile>
<createdBy>mgabua</createdBy>
<createdTime>2016-02-01 17:31:40 UTC</createdTime>
<ownerDesignName>maintenix</ownerDesignName>
<importedID>19B2213B-0EE8-94B4-8B22-C299C4101854</importedID>
<containerWithKeyObject>BBC81EB4-C798-A001-7313-36A9424625A4</containerWithKeyObject>
<deleteRule>NO ACTION</deleteRule>
<localFKIndex>90531095-B882-17CF-667C-B7578D128503</localFKIndex>
<keyObject>A9039AB9-0669-5B9F-B2B3-20842366F167</keyObject>
<mandatory>true</mandatory>
<transferable>true</transferable>
<columnDependencyConstraintGenerateInDDL>true</columnDependencyConstraintGenerateInDDL>
</FKIndexAssociation>