<?xml version = '1.0' encoding = 'UTF-8'?>
<FKIndexAssociation class="oracle.dbtools.crest.model.design.relational.FKIndexAssociation" directorySegmentName="seg_0" id="20CD1E24-0538-C305-A63F-6520A4A85CF4" name="FK_CBORGORG_POHEADER">
<sourceDDLFile>maintenix.sql</sourceDDLFile>
<createdBy>mgabua</createdBy>
<createdTime>2016-02-01 17:31:30 UTC</createdTime>
<ownerDesignName>maintenix</ownerDesignName>
<importedID>0D5FDDEE-772D-3C25-EECB-3705FA46F623</importedID>
<containerWithKeyObject>69886E2D-1693-0E77-4DA9-3171AA171207</containerWithKeyObject>
<deleteRule>NO ACTION</deleteRule>
<localFKIndex>DDD3FA61-F9F6-C76E-9369-6A7F09FB3755</localFKIndex>
<keyObject>2A9852CB-AE8F-F656-BC78-F6F7346500A3</keyObject>
<mandatory>true</mandatory>
<transferable>true</transferable>
<columnDependencyConstraintGenerateInDDL>true</columnDependencyConstraintGenerateInDDL>
</FKIndexAssociation>