<?xml version = '1.0' encoding = 'UTF-8'?>
<FKIndexAssociation class="oracle.dbtools.crest.model.design.relational.FKIndexAssociation" directorySegmentName="seg_1" id="232E6110-86F6-3BBE-2730-CBBB5090029C" name="FK_EQPASSMBLBOM_MIMPARTCHRDATA">
<sourceDDLFile>maintenix.sql</sourceDDLFile>
<createdBy>mgabua</createdBy>
<createdTime>2016-02-01 17:31:30 UTC</createdTime>
<ownerDesignName>maintenix</ownerDesignName>
<importedID>64E23391-ECB3-6216-3680-9D89B4E58876</importedID>
<containerWithKeyObject>78395DF8-3DEB-161A-57A2-971C3F3FA23F</containerWithKeyObject>
<deleteRule>NO ACTION</deleteRule>
<localFKIndex>508B3E4D-1D7F-FA17-2C16-43532287C942</localFKIndex>
<keyObject>FF22F16F-6617-16CC-DC44-134601F3D3D7</keyObject>
<mandatory>true</mandatory>
<transferable>true</transferable>
<columnDependencyConstraintGenerateInDDL>true</columnDependencyConstraintGenerateInDDL>
</FKIndexAssociation>