<?xml version = '1.0' encoding = 'UTF-8'?>
<FKIndexAssociation class="oracle.dbtools.crest.model.design.relational.FKIndexAssociation" directorySegmentName="seg_9" id="95A8E992-9834-BC14-77EC-27E86EB800B2" name="FK_MIMDB_REFFAILEFFECTTYPE">
<sourceDDLFile>maintenix.sql</sourceDDLFile>
<createdBy>mgabua</createdBy>
<createdTime>2016-02-01 17:31:32 UTC</createdTime>
<ownerDesignName>maintenix</ownerDesignName>
<importedID>1BA297A6-4C0E-528A-457D-17CA56F21DF3</importedID>
<containerWithKeyObject>A7AB0310-4D33-393F-DFE5-84C97DD17D62</containerWithKeyObject>
<deleteRule>NO ACTION</deleteRule>
<localFKIndex>D4B8EC93-1519-CD53-3B15-D4445610DEEC</localFKIndex>
<keyObject>E75B3E4D-77BD-54C9-7575-1EF9275C71EA</keyObject>
<mandatory>true</mandatory>
<transferable>true</transferable>
<columnDependencyConstraintGenerateInDDL>true</columnDependencyConstraintGenerateInDDL>
</FKIndexAssociation>