<?xml version = '1.0' encoding = 'UTF-8'?>
<FKIndexAssociation class="oracle.dbtools.crest.model.design.relational.FKIndexAssociation" directorySegmentName="seg_6" id="CFEF566B-E426-547D-EF70-F30196AF0A8F" name="FK_LPAFLEET_LPATURNWTYPE">
<sourceDDLFile>maintenix.sql</sourceDDLFile>
<createdBy>mgabua</createdBy>
<createdTime>2016-02-01 17:31:31 UTC</createdTime>
<ownerDesignName>maintenix</ownerDesignName>
<importedID>1E096C39-251F-0E01-C628-DE88E3070B72</importedID>
<containerWithKeyObject>ABF61AA5-63B1-A708-494E-5504C7D365A6</containerWithKeyObject>
<deleteRule>NO ACTION</deleteRule>
<localFKIndex>850D56A7-CFB3-E4FB-A5A4-D1BC82781DBD</localFKIndex>
<keyObject>4E6CBC0F-6F0D-E24D-9673-6A320F6E5686</keyObject>
<mandatory>true</mandatory>
<transferable>true</transferable>
<columnDependencyConstraintGenerateInDDL>true</columnDependencyConstraintGenerateInDDL>
</FKIndexAssociation>