<?xml version = '1.0' encoding = 'UTF-8'?>
<FKIndexAssociation class="oracle.dbtools.crest.model.design.relational.FKIndexAssociation" directorySegmentName="seg_22" id="44F0B5B3-CDEF-58B0-DDB7-EF33D5246E02" name="FK_ORGVENDOR_RFQVENDOR">
<sourceDDLFile>maintenix.sql</sourceDDLFile>
<createdBy>mgabua</createdBy>
<createdTime>2016-02-01 17:31:37 UTC</createdTime>
<ownerDesignName>maintenix</ownerDesignName>
<importedID>CA4E9BF6-6736-A1AA-6F0C-BD0996B9B579</importedID>
<containerWithKeyObject>087CE5F3-AF57-1FEF-1FF3-082237D7D473</containerWithKeyObject>
<deleteRule>NO ACTION</deleteRule>
<localFKIndex>6F386099-64DC-0026-A5F8-C57EA5047451</localFKIndex>
<keyObject>D0B3FD45-F014-9F45-27B8-347334355E1A</keyObject>
<mandatory>true</mandatory>
<transferable>true</transferable>
<columnDependencyConstraintGenerateInDDL>true</columnDependencyConstraintGenerateInDDL>
</FKIndexAssociation>