<?xml version = '1.0' encoding = 'UTF-8'?>
<FKIndexAssociation class="oracle.dbtools.crest.model.design.relational.FKIndexAssociation" directorySegmentName="seg_24" id="43311C9A-9C6F-312E-3CB1-3481A2741EFC" name="FK_PPCLOC_PPCLOCCAP">
<sourceDDLFile>maintenix.sql</sourceDDLFile>
<createdBy>mgabua</createdBy>
<createdTime>2016-02-01 17:31:38 UTC</createdTime>
<ownerDesignName>maintenix</ownerDesignName>
<importedID>ED2C9DBF-8C9D-FA25-E005-BB373E112B89</importedID>
<containerWithKeyObject>262EDFBC-218B-43AC-B9C0-FDE9481423CF</containerWithKeyObject>
<deleteRule>NO ACTION</deleteRule>
<localFKIndex>AF492745-3A47-777D-6E7C-A4B3937684D1</localFKIndex>
<keyObject>ACE9CAB8-F150-473F-384F-2574093F87C7</keyObject>
<mandatory>true</mandatory>
<transferable>true</transferable>
<columnDependencyConstraintGenerateInDDL>true</columnDependencyConstraintGenerateInDDL>
</FKIndexAssociation>