<?xml version = '1.0' encoding = 'UTF-8'?>
<TableProxyOraclev11g class="oracle.dbtools.crest.model.design.storage.oracle.v11g.TableProxyOraclev11g" name="REF_SHIPMENT_REASON" directorySegmentName="seg_4" id="89BF7F28-6A07-2F2F-56BA-1DF46D4C492B">
<createdBy>mgabua</createdBy>
<createdTime>2016-02-01 17:31:27 UTC</createdTime>
<ownerDesignName>maintenix</ownerDesignName>
<partitionedRowMovement>DISABLE</partitionedRowMovement>
<temporaryChanged>false</temporaryChanged>
<accessDriverType>oracle_loader</accessDriverType>
<rejectLimit></rejectLimit>
<columnProxies itemClass="oracle.dbtools.crest.model.design.storage.oracle.v12c.ColumnProxyOraclev12c">
<ColumnProxy name="SHIPMENT_REASON_DB_ID" id="04A3036C-8E70-3B3C-F75F-2A03378A2485">
<createdBy>mgabua</createdBy>
<createdTime>2016-02-01 17:31:29 UTC</createdTime>
<ownerDesignName>maintenix</ownerDesignName>
<deferrable>YES</deferrable>
<nncDeferrable>YES</nncDeferrable>
</ColumnProxy>
<ColumnProxy name="DESC_SDESC" id="0FD9A979-4028-1FC3-EC52-6235D060FA35">
<createdBy>mgabua</createdBy>
<createdTime>2016-02-01 17:31:29 UTC</createdTime>
<ownerDesignName>maintenix</ownerDesignName>
<nncDeferrable>YES</nncDeferrable>
</ColumnProxy>
<ColumnProxy name="REVISION_USER" id="1AE2A911-8AB8-EFB4-4077-A59D9EEBABFC">
<createdBy>mgabua</createdBy>
<createdTime>2016-02-01 17:31:29 UTC</createdTime>
<ownerDesignName>maintenix</ownerDesignName>
<nncDeferrable>YES</nncDeferrable>
</ColumnProxy>
<ColumnProxy name="SHIPMENT_TYPE_DB_ID" id="436393A8-DC13-3941-8333-BAD1C3331D8F">
<createdBy>mgabua</createdBy>
<createdTime>2016-02-01 17:31:29 UTC</createdTime>
<ownerDesignName>maintenix</ownerDesignName>
<deferrable>YES</deferrable>
<nncDeferrable>YES</nncDeferrable>
</ColumnProxy>
<ColumnProxy name="SHIPMENT_REASON_CD" id="48B5BB56-D7C9-35E5-39A3-DC56DAB1A2DA">
<createdBy>mgabua</createdBy>
<createdTime>2016-02-01 17:31:29 UTC</createdTime>
<ownerDesignName>maintenix</ownerDesignName>
<nncDeferrable>YES</nncDeferrable>
</ColumnProxy>
<ColumnProxy name="RSTAT_CD" id="95FBE0B2-2C55-61BE-794B-D708F41FA8D3">
<createdBy>mgabua</createdBy>
<createdTime>2016-02-01 17:31:29 UTC</createdTime>
<ownerDesignName>maintenix</ownerDesignName>
<deferrable>YES</deferrable>
<nncDeferrable>YES</nncDeferrable>
</ColumnProxy>
<ColumnProxy name="CREATION_DT" id="B2329636-BC83-321F-8958-E368E68481DA">
<createdBy>mgabua</createdBy>
<createdTime>2016-02-01 17:31:29 UTC</createdTime>
<ownerDesignName>maintenix</ownerDesignName>
<nncDeferrable>YES</nncDeferrable>
</ColumnProxy>
<ColumnProxy name="REVISION_DT" id="C0774E1C-B3CB-8A81-F4A7-89D03A7EB269">
<createdBy>mgabua</createdBy>
<createdTime>2016-02-01 17:31:29 UTC</createdTime>
<ownerDesignName>maintenix</ownerDesignName>
<nncDeferrable>YES</nncDeferrable>
</ColumnProxy>
<ColumnProxy name="REVISION_DB_ID" id="D5DF6391-C505-E848-454D-431CD86CB601">
<createdBy>mgabua</createdBy>
<createdTime>2016-02-01 17:31:29 UTC</createdTime>
<ownerDesignName>maintenix</ownerDesignName>
<deferrable>YES</deferrable>
<nncDeferrable>YES</nncDeferrable>
</ColumnProxy>
<ColumnProxy name="DESC_LDESC" id="DA9B22A4-F56E-D726-8B82-6E005FC32F32">
<createdBy>mgabua</createdBy>
<createdTime>2016-02-01 17:31:29 UTC</createdTime>
<ownerDesignName>maintenix</ownerDesignName>
</ColumnProxy>
<ColumnProxy name="SHIPMENT_TYPE_CD" id="DEE9EC1D-6972-3842-BC40-FA6C5C1C9C14">
<createdBy>mgabua</createdBy>
<createdTime>2016-02-01 17:31:29 UTC</createdTime>
<ownerDesignName>maintenix</ownerDesignName>
<nncDeferrable>YES</nncDeferrable>
</ColumnProxy>
</columnProxies>
<foreignKeys>
<ForeignKey class="oracle.dbtools.crest.model.design.storage.oracle.v10g.FKProxyOraclev10g" name="FK_REFSHIPTYPE_REFSHIPREASON" id="22D128DF-BEE4-6C7D-2BA2-0D17E15C89E3">
<createdBy>mgabua</createdBy>
<createdTime>2016-02-01 17:31:41 UTC</createdTime>
<ownerDesignName>maintenix</ownerDesignName>
<deferrable>YES</deferrable>
</ForeignKey>
<ForeignKey class="oracle.dbtools.crest.model.design.storage.oracle.v10g.FKProxyOraclev10g" name="FK_MIMRSTAT_REFSHIPMENTREASON" id="BA5A7F5C-430A-E475-3C89-83325D98DBFB">
<createdBy>mgabua</createdBy>
<createdTime>2016-02-01 17:31:35 UTC</createdTime>
<ownerDesignName>maintenix</ownerDesignName>
<deferrable>YES</deferrable>
</ForeignKey>
</foreignKeys>
<primaryKeys>
<PrimaryKey class="oracle.dbtools.crest.model.design.storage.oracle.v10g.PKProxyOraclev10g" name="pk_REF_SHIPMENT_REASON" id="E5578407-2105-994E-9B36-15E1DA575B9C">
<createdBy>mgabua</createdBy>
<createdTime>2016-02-01 17:31:29 UTC</createdTime>
<ownerDesignName>maintenix</ownerDesignName>
<nameHasQuotes>true</nameHasQuotes>
<indexSort>SORTED</indexSort>
</PrimaryKey>
</primaryKeys>
</TableProxyOraclev11g>