<?xml version = '1.0' encoding = 'UTF-8'?>
<FKIndexAssociation class="oracle.dbtools.crest.model.design.relational.FKIndexAssociation" directorySegmentName="seg_7" id="BCF54B69-FF4E-7CEA-F029-445F45E10E2C" name="FK_MIMDB_AUTORSRVQUEUE">
<sourceDDLFile>maintenix.sql</sourceDDLFile>
<createdBy>mgabua</createdBy>
<createdTime>2016-02-01 17:31:31 UTC</createdTime>
<ownerDesignName>maintenix</ownerDesignName>
<importedID>78B35081-1CAF-4A4C-B6C9-2636F8F88804</importedID>
<containerWithKeyObject>7B6BA1A6-2925-C3B3-01A9-A55E3F2071DA</containerWithKeyObject>
<deleteRule>NO ACTION</deleteRule>
<localFKIndex>237CD4CA-4BEA-597D-F26B-6D2BE40F6E35</localFKIndex>
<keyObject>E75B3E4D-77BD-54C9-7575-1EF9275C71EA</keyObject>
<mandatory>true</mandatory>
<transferable>true</transferable>
<columnDependencyConstraintGenerateInDDL>true</columnDependencyConstraintGenerateInDDL>
</FKIndexAssociation>