<?xml version="1.0" encoding="UTF-8" standalone="no"?>

<!--

 Control File

 This file manages the order of execution for the upgrades in this stream.
 The upgrades get executed in order from top to bottom.
 New entries should be inserted at the bottom of this file by default.

 Example:

  <include file="EXAMPLE-001.sql" relativeToChangelogFile="true"/>

-->

<databaseChangeLog
      xmlns="http://www.liquibase.org/xml/ns/dbchangelog"
      xmlns:xsi="http://www.w3.org/2001/XMLSchema-instance"
      xmlns:ext="http://www.liquibase.org/xml/ns/dbchangelog-ext"
      xsi:schemaLocation="http://www.liquibase.org/xml/ns/dbchangelog http://www.liquibase.org/xml/ns/dbchangelog/dbchangelog-3.0.xsd
      http://www.liquibase.org/xml/ns/dbchangelog-ext http://www.liquibase.org/xml/ns/dbchangelog/dbchangelog-ext.xsd">



	<!--  schema -->
	<!--  -->
	<include file="schema/oper-237.sql" relativeToChangelogFile="true"/>
	<!--  -->
	<!--  -->
	<include file="schema/oper-236.sql" relativeToChangelogFile="true"/>
	<!--  -->

	<!--  view -->
	<!--  -->
	<include file="view/oper-237-001.sql" relativeToChangelogFile="true"/>
	<!--  -->
	<include file="view/oper-237-002.sql" relativeToChangelogFile="true"/>
	<!--  -->
	<include file="view/oper-237-003.sql" relativeToChangelogFile="true"/>
	<!--  -->
	<include file="view/oper-237-004.sql" relativeToChangelogFile="true"/>
	<!--  -->
	<include file="view/oper-237-005.sql" relativeToChangelogFile="true"/>
	<!--  -->
	<include file="view/oper-237-006.sql" relativeToChangelogFile="true"/>
	<!--  -->
	<include file="view/oper-237-007.sql" relativeToChangelogFile="true"/>
	<!--  -->
	<include file="view/oper-237-008.sql" relativeToChangelogFile="true"/>
	<!--  -->
	<include file="view/oper-237-009.sql" relativeToChangelogFile="true"/>
	<!--  -->
	<include file="view/oper-237-010.sql" relativeToChangelogFile="true"/>
	<!--  -->
	<include file="view/oper-237-011.sql" relativeToChangelogFile="true"/>
	<!--  -->
	<include file="view/oper-237-014.sql" relativeToChangelogFile="true"/>
	<!--  -->
	<include file="view/oper-237-015.sql" relativeToChangelogFile="true"/>
	<!--  -->
	<!--  -->
	<include file="view/oper-236-001.sql" relativeToChangelogFile="true"/>
	<!--  -->
	<!--  -->
	<include file="view/oper-236-002.sql" relativeToChangelogFile="true"/>
	<!--  -->
	<include file="view/oper-398.sql" relativeToChangelogFile="true"/>

	<!--  plsql -->
	<!--  -->
	<include file="plsql/oper-237-001.sql" relativeToChangelogFile="true"/>
	<!--  -->
	<include file="plsql/oper-237-002.sql" relativeToChangelogFile="true"/>
	<!--  -->
	<!--  -->
	<include file="plsql/oper-237-003.sql" relativeToChangelogFile="true"/>
	<!--  -->
	<include file="plsql/oper-237-004.sql" relativeToChangelogFile="true"/>
	<!--  -->
	<!--  -->
	<include file="plsql/oper-410-001.sql" relativeToChangelogFile="true"/>
	<!--  -->
	<!--  -->
	<include file="plsql/oper-236-001.sql" relativeToChangelogFile="true"/>
	<!--  -->
	<!--  -->
	<include file="plsql/oper-236-002.sql" relativeToChangelogFile="true"/>
	<!--  -->
	<!--  -->
	<include file="plsql/oper-236-003.sql" relativeToChangelogFile="true"/>
	<!--  -->
	<!--  -->
	<include file="plsql/oper-236-004.sql" relativeToChangelogFile="true"/>
	<!--  -->
	<!--  -->
	<include file="plsql/dev-2470-001.sql" relativeToChangelogFile="true"/>
	<!--  -->
	<!--  -->
	<include file="plsql/dev-2470-002.sql" relativeToChangelogFile="true"/>
	<!--  -->
	<!--  -->
	<include file="plsql/mtx-949.sql" relativeToChangelogFile="true"/>
	<!--  -->

	<!--  data -->
	<!--  -->
	<include file="data/oper-237-001.sql" relativeToChangelogFile="true"/>
	<!--  -->
	<include file="data/oper-237-002.sql" relativeToChangelogFile="true"/>
	<!--  -->
	<include file="data/oper-237-003.sql" relativeToChangelogFile="true"/>
	<!--  -->
	<include file="data/oper-237-004.sql" relativeToChangelogFile="true"/>
	<!--  -->
	<include file="data/oper-415.sql" relativeToChangelogFile="true"/>

</databaseChangeLog>
