<?xml version = '1.0' encoding = 'UTF-8'?>
<FKIndexAssociation class="oracle.dbtools.crest.model.design.relational.FKIndexAssociation" directorySegmentName="seg_5" id="E69C9017-C1C3-EC91-C29E-866D54344C4D" name="FK_INVLOC_INVLOCPRINTER">
<sourceDDLFile>maintenix.sql</sourceDDLFile>
<createdBy>mgabua</createdBy>
<createdTime>2016-02-01 17:31:31 UTC</createdTime>
<ownerDesignName>maintenix</ownerDesignName>
<importedID>F38A6E33-5311-2E1A-56D5-18A35900675D</importedID>
<containerWithKeyObject>0035C223-E2AD-61D0-CD7C-3E62B8F9CAA2</containerWithKeyObject>
<deleteRule>NO ACTION</deleteRule>
<localFKIndex>FFFBA9CA-EB54-DF29-2709-90FA921C394D</localFKIndex>
<keyObject>E55DB47F-A505-96FC-D00F-EC674A612355</keyObject>
<mandatory>true</mandatory>
<transferable>true</transferable>
<columnDependencyConstraintGenerateInDDL>true</columnDependencyConstraintGenerateInDDL>
</FKIndexAssociation>