<?xml version = '1.0' encoding = 'UTF-8'?>
<FKIndexAssociation class="oracle.dbtools.crest.model.design.relational.FKIndexAssociation" directorySegmentName="seg_10" id="F104EC27-8CFB-CBAC-B5AD-0AD8BCF07FA8" name="FK_MIMDB_REFSCHEDPRIORITY">
<sourceDDLFile>maintenix.sql</sourceDDLFile>
<createdBy>mgabua</createdBy>
<createdTime>2016-02-01 17:31:32 UTC</createdTime>
<ownerDesignName>maintenix</ownerDesignName>
<importedID>6E6F4648-BFEC-7E27-DCDE-4DAEF71329CA</importedID>
<containerWithKeyObject>F379E76E-B26D-CC7D-C4F1-BADD561CCA17</containerWithKeyObject>
<deleteRule>NO ACTION</deleteRule>
<localFKIndex>B65C0606-3D4E-E058-9B98-3805EED9E1D6</localFKIndex>
<keyObject>E75B3E4D-77BD-54C9-7575-1EF9275C71EA</keyObject>
<mandatory>true</mandatory>
<transferable>true</transferable>
<columnDependencyConstraintGenerateInDDL>true</columnDependencyConstraintGenerateInDDL>
</FKIndexAssociation>