<?xml version = '1.0' encoding = 'UTF-8'?>
<FKIndexAssociation class="oracle.dbtools.crest.model.design.relational.FKIndexAssociation" directorySegmentName="seg_21" id="E7FDB7F2-D7E6-BA14-5D06-9A6C8E5BBB41" name="FK_ORGHR_ORGHRSHIFT">
<sourceDDLFile>maintenix.sql</sourceDDLFile>
<createdBy>mgabua</createdBy>
<createdTime>2016-02-01 17:31:37 UTC</createdTime>
<ownerDesignName>maintenix</ownerDesignName>
<importedID>10521109-4162-9A73-7F7B-D4CBB666826B</importedID>
<containerWithKeyObject>93907696-2C7E-5D89-1D58-B85C9660899D</containerWithKeyObject>
<deleteRule>NO ACTION</deleteRule>
<localFKIndex>ECE2ABD4-180A-E3B9-94E9-DA79A13A0ED2</localFKIndex>
<keyObject>4DC0A1A5-6621-84B2-639E-C929E147517E</keyObject>
<mandatory>true</mandatory>
<transferable>true</transferable>
<columnDependencyConstraintGenerateInDDL>true</columnDependencyConstraintGenerateInDDL>
</FKIndexAssociation>