<?xml version = '1.0' encoding = 'UTF-8'?>
<FKIndexAssociation class="oracle.dbtools.crest.model.design.relational.FKIndexAssociation" directorySegmentName="seg_14" id="5C9E17CA-10AC-D029-EAC0-82EAB6390B9F" name="FK_MIMRSTAT_INVCURRUSAGE">
<sourceDDLFile>maintenix.sql</sourceDDLFile>
<createdBy>mgabua</createdBy>
<createdTime>2016-02-01 17:31:33 UTC</createdTime>
<ownerDesignName>maintenix</ownerDesignName>
<importedID>66861ADA-5BC1-4FF1-7B75-3F900DADEB09</importedID>
<containerWithKeyObject>7550C4B7-97A6-08F5-DADE-A62751229AB5</containerWithKeyObject>
<deleteRule>NO ACTION</deleteRule>
<localFKIndex>1F875DB6-7B34-A182-F60B-94CDEBDCC687</localFKIndex>
<keyObject>26C9B8F4-9380-3DA2-8CC7-E2DF3B988D89</keyObject>
<mandatory>true</mandatory>
<transferable>true</transferable>
<columnDependencyConstraintGenerateInDDL>true</columnDependencyConstraintGenerateInDDL>
</FKIndexAssociation>