<?xml version = '1.0' encoding = 'UTF-8'?>
<Diagram class="oracle.dbtools.crest.swingui.relational.DPVRelationalSubView" name="Event: Tasks: Resources &amp; Scheduling" id="6CF7D93A-1721-697F-F7D8-B738C646FE40">
<createdBy>mgabua</createdBy>
<modifiedBy>mgabua</modifiedBy>
<createdTime>2017-08-14 17:49:17 UTC</createdTime>
<autoRoute>false</autoRoute>
<boxInbox>true</boxInbox>
<showLegend>false</showLegend>
<showLabels>false</showLabels>
<showRelAttributes>false</showRelAttributes>
<gridEnabled>false</gridEnabled>
<showGrid>false</showGrid>
<diagramColor>-1</diagramColor>
<display>false</display>
<notation>1</notation>
<objectViews>
<OView class="oracle.dbtools.crest.swingui.relational.TVTable" oid="16E6D813-9266-731F-7316-8074BB1FEC7F" otype="Table" vid="933EEB89-10C0-AEB7-35B3-30BDC18B54AA">
<hideElementsInCurrentOnly>false</hideElementsInCurrentOnly>
<bounds x="618" y="0" width="524" height="200"/>
</OView>
<OView class="oracle.dbtools.crest.swingui.relational.TVTable" oid="27349C44-F31E-76E6-CC81-7663ADB2677F" otype="Table" vid="234E19F8-0BFC-75AC-89C9-34FEA3775B0F">
<hideElementsInCurrentOnly>false</hideElementsInCurrentOnly>
<bounds x="866" y="2390" width="353" height="248"/>
</OView>
<OView class="oracle.dbtools.crest.swingui.relational.TVTable" oid="404CBF60-2061-10BA-B225-436A6C0F3964" otype="Table" vid="EC5DC927-B367-F1BD-D26C-C807F073BFF9">
<hideElementsInCurrentOnly>false</hideElementsInCurrentOnly>
<bounds x="0" y="384" width="520" height="1584"/>
</OView>
<OView class="oracle.dbtools.crest.swingui.relational.TVTable" oid="44544249-E576-F8A4-5015-58C8C8E36826" otype="Table" vid="EC925282-040D-51EC-20DB-68A49AC36395">
<hideElementsInCurrentOnly>false</hideElementsInCurrentOnly>
<bounds x="742" y="2077" width="503" height="248"/>
</OView>
<OView class="oracle.dbtools.crest.swingui.relational.TVTable" oid="4A2B637D-ABEC-0B07-6A00-C8532705FC2E" otype="Table" vid="2778E6C7-519D-E5F4-CD01-321B57756E1C">
<hideElementsInCurrentOnly>false</hideElementsInCurrentOnly>
<bounds x="0" y="2782" width="511" height="408"/>
</OView>
<OView class="oracle.dbtools.crest.swingui.relational.TVTable" oid="4FA9A6AB-CB26-AC80-208F-3009BC16A98E" otype="Table" vid="FDA09585-81EB-C21F-C28C-4AC9581F303C">
<hideElementsInCurrentOnly>false</hideElementsInCurrentOnly>
<bounds x="721" y="1698" width="234" height="259"/>
</OView>
<OView class="oracle.dbtools.crest.swingui.relational.TVTable" oid="56C25CFF-DEAD-A2D8-4D9F-B7C481C9619A" otype="Table" vid="83D6FAAE-B569-495A-4EF8-EB68590A35A7">
<hideElementsInCurrentOnly>false</hideElementsInCurrentOnly>
<bounds x="1059" y="1202" width="411" height="408"/>
</OView>
<OView class="oracle.dbtools.crest.swingui.relational.TVTable" oid="5CE8984D-9D97-2929-9D51-3F7880F9EDDE" otype="Table" vid="3DC572E4-70A8-C019-5EF6-9DC07A33FF79">
<hideElementsInCurrentOnly>false</hideElementsInCurrentOnly>
<bounds x="756" y="3217" width="345" height="304"/>
</OView>
<OView class="oracle.dbtools.crest.swingui.relational.TVTable" oid="66B73DC7-0031-5174-1DC9-1F1FEF5AAD86" otype="Table" vid="C8AA7E5C-3FE6-A6DA-0872-7220433555D1">
<hideElementsInCurrentOnly>false</hideElementsInCurrentOnly>
<bounds x="640" y="532" width="401" height="248"/>
</OView>
<OView class="oracle.dbtools.crest.swingui.relational.TVTable" oid="72075EC3-C7F8-C697-1601-7053FE82BA74" otype="Table" vid="B7AB338F-541E-95F2-B7D4-D1BC83D75684">
<hideElementsInCurrentOnly>false</hideElementsInCurrentOnly>
<bounds x="0" y="0" width="538" height="324"/>
</OView>
<OView class="oracle.dbtools.crest.swingui.relational.TVTable" oid="7AE21941-331F-6AAA-B41D-F30D7DBCF9C8" otype="Table" vid="C2EEDBBB-3B68-DA99-1320-45D39539141E">
<hideElementsInCurrentOnly>false</hideElementsInCurrentOnly>
<bounds x="994" y="787" width="612" height="352"/>
</OView>
<OView class="oracle.dbtools.crest.swingui.relational.TVTable" oid="9AA79F32-DAEB-2FB8-A6C2-EB8A053C2185" otype="Table" vid="A1C28EF5-3ED9-1DDC-854F-50ECD22E2F0C">
<hideElementsInCurrentOnly>false</hideElementsInCurrentOnly>
<bounds x="590" y="2801" width="499" height="366"/>
</OView>
<OView class="oracle.dbtools.crest.swingui.relational.TVTable" oid="A72B19C4-9B25-E694-3687-97E567B2C180" otype="Table" vid="8D4E6DCD-739E-0647-126C-E270C769DC17">
<hideElementsInCurrentOnly>false</hideElementsInCurrentOnly>
<bounds x="649" y="302" width="388" height="192"/>
</OView>
<OView class="oracle.dbtools.crest.swingui.relational.TVTable" oid="B69056A5-EEC8-D3AD-2CDE-01DAF33B101D" otype="Table" vid="106623E9-12C5-0816-B059-508BAEC560D7">
<hideElementsInCurrentOnly>false</hideElementsInCurrentOnly>
<bounds x="0" y="3304" width="430" height="262"/>
</OView>
<OView class="oracle.dbtools.crest.swingui.relational.TVTable" oid="C3979FE7-A466-F175-FEC6-8D49F22EE538" otype="Table" vid="21DE5798-FD89-72BA-ED37-8767513A343A">
<hideElementsInCurrentOnly>false</hideElementsInCurrentOnly>
<bounds x="0" y="2059" width="655" height="646"/>
</OView>
<OView class="oracle.dbtools.crest.swingui.relational.TVTable" oid="F464A653-5AD2-01D4-DFE6-24E30D69F968" otype="Table" vid="EEA901E8-92E8-4103-8981-204632300C6E">
<hideElementsInCurrentOnly>false</hideElementsInCurrentOnly>
<bounds x="1353" y="1677" width="524" height="660"/>
</OView>
</objectViews>
<connectors>
<Connector class="oracle.dbtools.crest.swingui.relational.TVFKRelation" oid="1FA2B79D-7DCC-E04F-C6FD-9FFACECB98A9" otype="FKIndexAssociation" vid_source="EC5DC927-B367-F1BD-D26C-C807F073BFF9" vid_target="EC5DC927-B367-F1BD-D26C-C807F073BFF9">
<hideElementsInCurrentOnly>false</hideElementsInCurrentOnly>
<lineWidth>1</lineWidth>
<points>
<point x="520" y="1176"/>
<point x="545" y="1176"/>
<point x="545" y="1993"/>
<point x="260" y="1993"/>
<point x="260" y="1968"/>
</points>
</Connector>
<Connector class="oracle.dbtools.crest.swingui.relational.TVFKRelation" oid="1FED9CF0-74D9-2FB2-ED25-86B45BEB8AC9" otype="FKIndexAssociation" vid_source="EC5DC927-B367-F1BD-D26C-C807F073BFF9" vid_target="21DE5798-FD89-72BA-ED37-8767513A343A">
<hideElementsInCurrentOnly>false</hideElementsInCurrentOnly>
<lineWidth>1</lineWidth>
<points>
<point x="270" y="1968"/>
<point x="270" y="2059"/>
</points>
</Connector>
<Connector class="oracle.dbtools.crest.swingui.relational.TVFKRelation" oid="26EE9C8F-CABF-3EAE-3F9D-6AA50C0FE84D" otype="FKIndexAssociation" vid_source="EC5DC927-B367-F1BD-D26C-C807F073BFF9" vid_target="83D6FAAE-B569-495A-4EF8-EB68590A35A7">
<hideElementsInCurrentOnly>false</hideElementsInCurrentOnly>
<lineWidth>1</lineWidth>
<points>
<point x="520" y="1416"/>
<point x="1059" y="1416"/>
</points>
</Connector>
<Connector class="oracle.dbtools.crest.swingui.relational.TVFKRelation" oid="2B93A324-E62C-3AFB-8047-FE172F33D744" otype="FKIndexAssociation" vid_source="EC5DC927-B367-F1BD-D26C-C807F073BFF9" vid_target="B7AB338F-541E-95F2-B7D4-D1BC83D75684">
<hideElementsInCurrentOnly>false</hideElementsInCurrentOnly>
<lineWidth>1</lineWidth>
<points>
<point x="260" y="384"/>
<point x="260" y="324"/>
</points>
</Connector>
<Connector class="oracle.dbtools.crest.swingui.relational.TVFKRelation" oid="2C87377D-9730-535B-4A5C-D3EFF9E71280" otype="FKIndexAssociation" vid_source="21DE5798-FD89-72BA-ED37-8767513A343A" vid_target="EC5DC927-B367-F1BD-D26C-C807F073BFF9">
<hideElementsInCurrentOnly>false</hideElementsInCurrentOnly>
<lineWidth>1</lineWidth>
<points>
<point x="260" y="2059"/>
<point x="260" y="1968"/>
</points>
</Connector>
<Connector class="oracle.dbtools.crest.swingui.relational.TVFKRelation" oid="5EB1DBEE-5AB1-0FA3-5233-040AF3EF0302" otype="FKIndexAssociation" vid_source="EC5DC927-B367-F1BD-D26C-C807F073BFF9" vid_target="83D6FAAE-B569-495A-4EF8-EB68590A35A7">
<hideElementsInCurrentOnly>false</hideElementsInCurrentOnly>
<lineWidth>1</lineWidth>
<points>
<point x="520" y="1406"/>
<point x="1059" y="1406"/>
</points>
</Connector>
<Connector class="oracle.dbtools.crest.swingui.relational.TVFKRelation" oid="66415EC6-A756-1ACD-69DC-F4A531022B2F" otype="FKIndexAssociation" vid_source="933EEB89-10C0-AEB7-35B3-30BDC18B54AA" vid_target="B7AB338F-541E-95F2-B7D4-D1BC83D75684">
<hideElementsInCurrentOnly>false</hideElementsInCurrentOnly>
<lineWidth>1</lineWidth>
<points>
<point x="618" y="100"/>
<point x="538" y="100"/>
</points>
</Connector>
<Connector class="oracle.dbtools.crest.swingui.relational.TVFKRelation" oid="699BDFE7-6E92-BD70-AE40-3133A90149DD" otype="FKIndexAssociation" vid_source="21DE5798-FD89-72BA-ED37-8767513A343A" vid_target="2778E6C7-519D-E5F4-CD01-321B57756E1C">
<hideElementsInCurrentOnly>false</hideElementsInCurrentOnly>
<lineWidth>1</lineWidth>
<points>
<point x="255" y="2705"/>
<point x="255" y="2782"/>
</points>
</Connector>
<Connector class="oracle.dbtools.crest.swingui.relational.TVFKRelation" oid="7BE36704-C3A4-ECA3-C918-B18DE29B57A1" otype="FKIndexAssociation" vid_source="FDA09585-81EB-C21F-C28C-4AC9581F303C" vid_target="21DE5798-FD89-72BA-ED37-8767513A343A">
<hideElementsInCurrentOnly>false</hideElementsInCurrentOnly>
<lineWidth>1</lineWidth>
<points>
<point x="721" y="1827"/>
<point x="327" y="2059"/>
</points>
</Connector>
<Connector class="oracle.dbtools.crest.swingui.relational.TVFKRelation" oid="8C5E2DA0-F835-E167-8090-2324E3B28ADD" otype="FKIndexAssociation" vid_source="8D4E6DCD-739E-0647-126C-E270C769DC17" vid_target="EC5DC927-B367-F1BD-D26C-C807F073BFF9">
<hideElementsInCurrentOnly>false</hideElementsInCurrentOnly>
<lineWidth>1</lineWidth>
<points>
<point x="649" y="439"/>
<point x="520" y="439"/>
</points>
</Connector>
<Connector class="oracle.dbtools.crest.swingui.relational.TVFKRelation" oid="A565EAEB-58CA-26FB-F8CD-146D64C3C929" otype="FKIndexAssociation" vid_source="234E19F8-0BFC-75AC-89C9-34FEA3775B0F" vid_target="21DE5798-FD89-72BA-ED37-8767513A343A">
<hideElementsInCurrentOnly>false</hideElementsInCurrentOnly>
<lineWidth>1</lineWidth>
<points>
<point x="866" y="2514"/>
<point x="655" y="2514"/>
</points>
</Connector>
<Connector class="oracle.dbtools.crest.swingui.relational.TVFKRelation" oid="AA2A8668-2790-0BA9-DB8D-12E765CAECC5" otype="FKIndexAssociation" vid_source="EC5DC927-B367-F1BD-D26C-C807F073BFF9" vid_target="EC5DC927-B367-F1BD-D26C-C807F073BFF9">
<hideElementsInCurrentOnly>false</hideElementsInCurrentOnly>
<lineWidth>1</lineWidth>
<points>
<point x="520" y="1176"/>
<point x="570" y="1176"/>
<point x="570" y="2018"/>
<point x="260" y="2018"/>
<point x="260" y="1968"/>
</points>
</Connector>
<Connector class="oracle.dbtools.crest.swingui.relational.TVFKRelation" oid="AABA75F7-55B5-9211-A8C5-A6290727298D" otype="FKIndexAssociation" vid_source="106623E9-12C5-0816-B059-508BAEC560D7" vid_target="2778E6C7-519D-E5F4-CD01-321B57756E1C">
<hideElementsInCurrentOnly>false</hideElementsInCurrentOnly>
<lineWidth>1</lineWidth>
<points>
<point x="215" y="3304"/>
<point x="215" y="3190"/>
</points>
</Connector>
<Connector class="oracle.dbtools.crest.swingui.relational.TVFKRelation" oid="C560D5D3-BF18-3C0C-0B4D-90C68CFD322B" otype="FKIndexAssociation" vid_source="C8AA7E5C-3FE6-A6DA-0872-7220433555D1" vid_target="EC5DC927-B367-F1BD-D26C-C807F073BFF9">
<hideElementsInCurrentOnly>false</hideElementsInCurrentOnly>
<lineWidth>1</lineWidth>
<points>
<point x="640" y="656"/>
<point x="520" y="656"/>
</points>
</Connector>
<Connector class="oracle.dbtools.crest.swingui.relational.TVFKRelation" oid="E5D8B551-3722-11D4-4A51-5FB0331EE27C" otype="FKIndexAssociation" vid_source="21DE5798-FD89-72BA-ED37-8767513A343A" vid_target="A1C28EF5-3ED9-1DDC-854F-50ECD22E2F0C">
<hideElementsInCurrentOnly>false</hideElementsInCurrentOnly>
<lineWidth>1</lineWidth>
<points>
<point x="622" y="2705"/>
<point x="622" y="2801"/>
</points>
</Connector>
<Connector class="oracle.dbtools.crest.swingui.relational.TVFKRelation" oid="E81FFF11-0675-3BE0-A60F-4E6D2468186A" otype="FKIndexAssociation" vid_source="EEA901E8-92E8-4103-8981-204632300C6E" vid_target="EC5DC927-B367-F1BD-D26C-C807F073BFF9">
<hideElementsInCurrentOnly>false</hideElementsInCurrentOnly>
<lineWidth>1</lineWidth>
<points>
<point x="1353" y="1822"/>
<point x="520" y="1822"/>
</points>
</Connector>
<Connector class="oracle.dbtools.crest.swingui.relational.TVFKRelation" oid="F0189938-B3BE-4494-AD8A-FFB25B0CA31E" otype="FKIndexAssociation" vid_source="EC5DC927-B367-F1BD-D26C-C807F073BFF9" vid_target="C2EEDBBB-3B68-DA99-1320-45D39539141E">
<hideElementsInCurrentOnly>false</hideElementsInCurrentOnly>
<lineWidth>1</lineWidth>
<points>
<point x="520" y="963"/>
<point x="994" y="963"/>
</points>
</Connector>
<Connector class="oracle.dbtools.crest.swingui.relational.TVFKRelation" oid="F14D0EE5-6125-C233-274D-353F6E57E406" otype="FKIndexAssociation" vid_source="EC925282-040D-51EC-20DB-68A49AC36395" vid_target="21DE5798-FD89-72BA-ED37-8767513A343A">
<hideElementsInCurrentOnly>false</hideElementsInCurrentOnly>
<lineWidth>1</lineWidth>
<points>
<point x="742" y="2201"/>
<point x="655" y="2201"/>
</points>
</Connector>
<Connector class="oracle.dbtools.crest.swingui.relational.TVFKRelation" oid="F3513B6E-1CEB-2041-C630-65F4BAA6F670" otype="FKIndexAssociation" vid_source="3DC572E4-70A8-C019-5EF6-9DC07A33FF79" vid_target="106623E9-12C5-0816-B059-508BAEC560D7">
<hideElementsInCurrentOnly>false</hideElementsInCurrentOnly>
<lineWidth>1</lineWidth>
<points>
<point x="756" y="3412"/>
<point x="430" y="3412"/>
</points>
</Connector>
</connectors>
</Diagram>