<?xml version = '1.0' encoding = 'UTF-8'?>
<FKIndexAssociation class="oracle.dbtools.crest.model.design.relational.FKIndexAssociation" directorySegmentName="seg_30" id="D7452887-993F-65E9-A7B4-5E0E04C1BD66" name="FK_RSTAT_PPCLOCEX">
<sourceDDLFile>maintenix.sql</sourceDDLFile>
<createdBy>mgabua</createdBy>
<createdTime>2016-02-01 17:31:42 UTC</createdTime>
<ownerDesignName>maintenix</ownerDesignName>
<importedID>7A695A96-D9C4-20AF-7D4B-F4AC5F4D81DA</importedID>
<containerWithKeyObject>48F9AFFF-914A-F2C0-2C25-E43F13F104BE</containerWithKeyObject>
<deleteRule>NO ACTION</deleteRule>
<localFKIndex>14A92404-EB69-0125-3335-D4DBBA775790</localFKIndex>
<keyObject>26C9B8F4-9380-3DA2-8CC7-E2DF3B988D89</keyObject>
<mandatory>true</mandatory>
<transferable>true</transferable>
<columnDependencyConstraintGenerateInDDL>true</columnDependencyConstraintGenerateInDDL>
</FKIndexAssociation>