<?xml version = '1.0' encoding = 'UTF-8'?>
<FKIndexAssociation class="oracle.dbtools.crest.model.design.relational.FKIndexAssociation" directorySegmentName="seg_13" id="0373AD41-5FDE-BD58-246B-68F6C98C955D" name="FK_MIMRSTAT_EQPMANUFACT">
<sourceDDLFile>maintenix.sql</sourceDDLFile>
<createdBy>mgabua</createdBy>
<createdTime>2016-02-01 17:31:33 UTC</createdTime>
<ownerDesignName>maintenix</ownerDesignName>
<importedID>D945E7C4-C88B-180F-1E47-AD1E7F21EA2C</importedID>
<containerWithKeyObject>13117F6A-3675-6B0F-2ECF-52FD15AF0B02</containerWithKeyObject>
<deleteRule>NO ACTION</deleteRule>
<localFKIndex>67363A51-342A-1A83-289E-CD0A7545DEBA</localFKIndex>
<keyObject>26C9B8F4-9380-3DA2-8CC7-E2DF3B988D89</keyObject>
<mandatory>true</mandatory>
<transferable>true</transferable>
<columnDependencyConstraintGenerateInDDL>true</columnDependencyConstraintGenerateInDDL>
</FKIndexAssociation>