<?xml version = '1.0' encoding = 'UTF-8'?>
<FKIndexAssociation class="oracle.dbtools.crest.model.design.relational.FKIndexAssociation" directorySegmentName="seg_13" id="32701AE1-87B0-2B64-A6B6-ED2DFFC17A3B" name="FK_MIMRSTAT_EQPOILTHRESHCARR">
<sourceDDLFile>maintenix.sql</sourceDDLFile>
<createdBy>mgabua</createdBy>
<createdTime>2016-02-01 17:31:33 UTC</createdTime>
<ownerDesignName>maintenix</ownerDesignName>
<importedID>F04076B2-DBF2-34CF-C6DB-ADF4C00DC3E0</importedID>
<containerWithKeyObject>A36C6C6D-25F2-23E3-361B-4C3E903A61DB</containerWithKeyObject>
<deleteRule>NO ACTION</deleteRule>
<localFKIndex>806E4981-06F6-5DA8-52A7-13ECF78F3AAE</localFKIndex>
<keyObject>26C9B8F4-9380-3DA2-8CC7-E2DF3B988D89</keyObject>
<mandatory>true</mandatory>
<transferable>true</transferable>
<columnDependencyConstraintGenerateInDDL>true</columnDependencyConstraintGenerateInDDL>
</FKIndexAssociation>